video2tfrecord/__init__.py
video2tfrecord/test.py
video2tfrecord/video2tfrecord.py
video2tfrecord-1.1.dist-info/METADATA
video2tfrecord-1.1.dist-info/RECORD
video2tfrecord-1.1.dist-info/WHEEL
video2tfrecord-1.1.dist-info/top_level.txt
