Metadata-Version: 2.1
Name: video2tfrecord
Version: 1.1
Summary: Easily convert RGB video data (e.g. .avi) to the TensorFlow tfrecord file format for training e.g. a NN in TensorFlow.
Home-page: https://ferreirafabio.github.io/
Author: Fabio Ferreira
Author-email: fabioferreira@mailbox.org
License: UNKNOWN
Download-URL: https://github.com/ferreirafabio/video2tfrecord
Keywords: tensorflow,neural networks,tfrecord,video
Platform: UNKNOWN
Classifier: Programming Language :: Python
Classifier: Programming Language :: Python :: 3
Classifier: Development Status :: 5 - Production/Stable
Classifier: Environment :: Other Environment
Classifier: Intended Audience :: Developers
Classifier: License :: OSI Approved :: MIT License
Classifier: Operating System :: OS Independent
Classifier: Topic :: Scientific/Engineering :: Artificial Intelligence
